coastalbook/__init__.py
coastalbook/geometries.py
coastalbook/hidden.py
coastalbook/maps.py
coastalbook/transform.py
coastalbook-0.1.3.dist-info/LICENSE
coastalbook-0.1.3.dist-info/METADATA
coastalbook-0.1.3.dist-info/WHEEL
coastalbook-0.1.3.dist-info/RECORD
