Metadata-Version: 2.1
Name: coastalbook
Version: 0.1.3
Summary: Jupyterbook for Delft Technical University Coastal Systems
License: MIT
Author: Floris Calkoen
Requires-Python: >=3.10,<4.0
Classifier: License :: OSI Approved :: MIT License
Classifier: Programming Language :: Python :: 3
Classifier: Programming Language :: Python :: 3.10
Classifier: Programming Language :: Python :: 3.11
Requires-Dist: pytest (>=7.4.0,<8.0.0)
